webbrowser_open/__init__.py
webbrowser_open/__main__.py
webbrowser_open/_linux.py
webbrowser_open/_mac.py
webbrowser_open/_win.py
webbrowser_open-0.2.1.dist-info/LICENSE
webbrowser_open-0.2.1.dist-info/METADATA
webbrowser_open-0.2.1.dist-info/WHEEL
webbrowser_open-0.2.1.dist-info/top_level.txt
webbrowser_open-0.2.1.dist-info/RECORD
