Metadata-Version: 2.2
Name: webbrowser_open
Version: 0.2.1
Summary: Prototype for stdlib webbrowser.open functionality
Author-email: Min RK <benjaminrk@gmail.com>
License: BSD-3-Clause
Project-URL: Homepage, https://github.com/minrk/webbrowser_open
Project-URL: Source, https://github.com/minrk/webbrowser_open
Project-URL: Tracker, https://github.com/minrk/webbrowser_open/issues
Keywords: webbrowser
Classifier: Development Status :: 1 - Planning
Classifier: Intended Audience :: Developers
Classifier: Programming Language :: Python
Classifier: Programming Language :: Python :: 3
Requires-Python: >=3.9
License-File: LICENSE
Provides-Extra: test
Requires-Dist: pytest; extra == "test"
